pyqtconsole/__init__.py
pyqtconsole/autocomplete.py
pyqtconsole/commandhistory.py
pyqtconsole/console.py
pyqtconsole/highlighter.py
pyqtconsole/interpreter.py
pyqtconsole/prompt.py
pyqtconsole/stream.py
pyqtconsole/text.py
pyqtconsole-1.2.3.dist-info/LICENSE
pyqtconsole-1.2.3.dist-info/METADATA
pyqtconsole-1.2.3.dist-info/WHEEL
pyqtconsole-1.2.3.dist-info/top_level.txt
pyqtconsole-1.2.3.dist-info/zip-safe
pyqtconsole-1.2.3.dist-info/RECORD
