Metadata-Version: 2.1
Name: pyqtconsole
Version: 1.2.3
Summary: Light weight python interpreter, easy to embed into Qt applications
Home-page: https://github.com/marcus-oscarsson/pyqtconsole
Author: Marcus Oskarsson
Author-email: marcus.oscarsson@esrf.fr
License: MIT
Keywords: interactive interpreter console shell autocompletion jedi qt
Classifier: Environment :: X11 Applications :: Qt
Classifier: Intended Audience :: Developers
Classifier: Operating System :: OS Independent
Classifier: Programming Language :: Python :: 2.7
Classifier: Programming Language :: Python :: 3
Classifier: Topic :: Software Development :: Interpreters
Classifier: Topic :: Software Development :: User Interfaces
Requires-Python: >=2.7
License-File: LICENSE
Requires-Dist: qtpy
Requires-Dist: jedi
